ScrollableContainers/__init__.py
ScrollableContainers/_qt5.py
ScrollableContainers/_qt6.py
ScrollableContainers/_tk.py
ScrollableContainers/_wx.py
scrollablecontainers-2.2.5.dist-info/METADATA
scrollablecontainers-2.2.5.dist-info/WHEEL
scrollablecontainers-2.2.5.dist-info/licenses/COPYING.md
scrollablecontainers-2.2.5.dist-info/RECORD
