Metadata-Version: 2.4
Name: ScrollableContainers
Version: 2.2.5
Summary: Scrollable containers for Tkinter, wxPython, PyQt5 and PyQt6
Project-URL: Homepage, https://github.com/tfpf/ScrollableContainers
Project-URL: Bug Tracker, https://github.com/tfpf/ScrollableContainers/issues
Author: Vishal Pankaj Chandratreya
License-File: COPYING.md
Classifier: License :: OSI Approved :: GNU General Public License v3 (GPLv3)
Classifier: Operating System :: OS Independent
Classifier: Programming Language :: Python :: 3
Requires-Python: >=3.10
Provides-Extra: qt5
Requires-Dist: pyqt5; extra == 'qt5'
Provides-Extra: qt6
Requires-Dist: pyqt6; extra == 'qt6'
Provides-Extra: wx
Requires-Dist: wxpython; extra == 'wx'
